dlt645/__init__.py
dlt645/__meta__.py
dlt645/cli.py
dlt645/constants.py
dlt645/exceptions.py
python_dlt645-0.1.3.dist-info/entry_points.txt
python_dlt645-0.1.3.dist-info/LICENSE
python_dlt645-0.1.3.dist-info/WHEEL
python_dlt645-0.1.3.dist-info/METADATA
python_dlt645-0.1.3.dist-info/RECORD
