Metadata-Version: 2.1
Name: python-dlt645
Version: 0.1.3
Summary: A basic DL/T645-2007 communication implementation
Home-page: https://github.com/gams/python-dlt645
License: MIT
Author: Stefan 'hr' Berder
Author-email: stefan@measureofquality.com
Requires-Python: >=3.9,<4.0
Classifier: License :: OSI Approved :: MIT License
Classifier: Programming Language :: Python :: 3
Classifier: Programming Language :: Python :: 3.9
Classifier: Programming Language :: Python :: 3.10
Classifier: Programming Language :: Python :: 3.11
Provides-Extra: cli
Requires-Dist: pyserial (>=3.5,<4.0); extra == "cli"
Project-URL: Documentation, https://python-dlt645.readthedocs.io/en/latest/
Project-URL: Repository, https://github.com/gams/python-dlt645
